byted_overpass_life_alliance_task_pack/__init__.py
byted_overpass_life_alliance_task_pack-0.0.1.dist-info/METADATA
byted_overpass_life_alliance_task_pack-0.0.1.dist-info/WHEEL
byted_overpass_life_alliance_task_pack-0.0.1.dist-info/top_level.txt
byted_overpass_life_alliance_task_pack-0.0.1.dist-info/RECORD
